op/__init__.py
op/logger.py
opu-0.0.1.dist-info/LICENSE
opu-0.0.1.dist-info/METADATA
opu-0.0.1.dist-info/WHEEL
opu-0.0.1.dist-info/top_level.txt
opu-0.0.1.dist-info/RECORD
