Metadata-Version: 2.1
Name: opu
Version: 0.0.1
Summary: Utilities for quick automation
Home-page: https://github.com/positivedefinite/op
Author: Oskar Person
Author-email: 
License: AGPL v3.0
Platform: UNKNOWN
Classifier: Programming Language :: Python :: 3
Classifier: License :: OSI Approved :: MIT License
Classifier: Operating System :: OS Independent
Requires-Python: >=3.6
